{
  "$schema": "node_modules/wrangler/config-schema.json",
  "name": "mlh-fellowship-scout",
  "main": ".open-next/worker.js",
  "assets": {
    "directory": ".open-next/assets",
    "binding": "ASSETS"
  },
  "compatibility_date": "2025-01-09",
  "compatibility_flags": [
    "nodejs_compat"
  ],
  "observability": {
    "enabled": true
  },
  "placement": { "mode": "smart" },
  "d1_databases": [{ "binding": "prod-db", "database_name": "mlh-fellowship-scout", "database_id": "5dfb4127-0120-4792-b686-a102f0fdf2b5" }]
}
